litests/__init__.py
litests/models.py
litests/pipeline.py
litests/adapter/__init__.py
litests/adapter/audiodevice.py
litests/adapter/base.py
litests/adapter/http.py
litests/adapter/websocket.py
litests/llm/__init__.py
litests/llm/base.py
litests/llm/chatgpt.py
litests/llm/claude.py
litests/llm/dify.py
litests/llm/gemini.py
litests/llm/litellm.py
litests/llm/context_manager/__init__.py
litests/llm/context_manager/base.py
litests/llm/context_manager/postgres.py
litests/performance_recorder/__init__.py
litests/performance_recorder/base.py
litests/performance_recorder/postgres.py
litests/performance_recorder/sqlite.py
litests/stt/__init__.py
litests/stt/azure.py
litests/stt/base.py
litests/stt/google.py
litests/stt/openai.py
litests/tts/__init__.py
litests/tts/azure.py
litests/tts/base.py
litests/tts/google.py
litests/tts/openai.py
litests/tts/speech_gateway.py
litests/tts/voicevox.py
litests/vad/__init__.py
litests/vad/base.py
litests/vad/standard.py
litests/voice_recorder/__init__.py
litests/voice_recorder/azure_storage.py
litests/voice_recorder/base.py
litests/voice_recorder/file.py
litests-0.3.12.dist-info/LICENSE
litests-0.3.12.dist-info/METADATA
litests-0.3.12.dist-info/WHEEL
litests-0.3.12.dist-info/top_level.txt
litests-0.3.12.dist-info/RECORD
