Metadata-Version: 2.1
Name: litests
Version: 0.3.12
Summary: A super lightweight Speech-to-Speech framework with modular VAD, STT, LLM and TTS components. 🧩
Home-page: https://github.com/uezo/litests
Author: uezo
Author-email: uezo@uezo.net
Maintainer: uezo
Maintainer-email: uezo@uezo.net
License: Apache v2
Classifier: Programming Language :: Python :: 3
License-File: LICENSE
Requires-Dist: httpx>=0.27.0
Requires-Dist: openai>=1.55.3
Requires-Dist: aiofiles>=24.1.0
